streamlit_multi_row_inputs/__init__.py
streamlit_multi_row_inputs/frontend/build/asset-manifest.json
streamlit_multi_row_inputs/frontend/build/bootstrap.min.css
streamlit_multi_row_inputs/frontend/build/index.html
streamlit_multi_row_inputs/frontend/build/precache-manifest.f4354877b4c1d9f05b6affdf0c317759.js
streamlit_multi_row_inputs/frontend/build/service-worker.js
streamlit_multi_row_inputs/frontend/build/static/js/2.5a800681.chunk.js
streamlit_multi_row_inputs/frontend/build/static/js/2.5a800681.chunk.js.LICENSE.txt
streamlit_multi_row_inputs/frontend/build/static/js/2.5a800681.chunk.js.map
streamlit_multi_row_inputs/frontend/build/static/js/main.bc13f73f.chunk.js
streamlit_multi_row_inputs/frontend/build/static/js/main.bc13f73f.chunk.js.map
streamlit_multi_row_inputs/frontend/build/static/js/runtime-main.1765f872.js
streamlit_multi_row_inputs/frontend/build/static/js/runtime-main.1765f872.js.map
streamlit_multi_textarea/__init__.py
streamlit_multi_textarea/frontend/build/asset-manifest.json
streamlit_multi_textarea/frontend/build/bootstrap.min.css
streamlit_multi_textarea/frontend/build/index.html
streamlit_multi_textarea/frontend/build/precache-manifest.e83d2a03ff162fe4d5de3403da557fdc.js
streamlit_multi_textarea/frontend/build/service-worker.js
streamlit_multi_textarea/frontend/build/static/js/2.e4606493.chunk.js
streamlit_multi_textarea/frontend/build/static/js/2.e4606493.chunk.js.LICENSE.txt
streamlit_multi_textarea/frontend/build/static/js/2.e4606493.chunk.js.map
streamlit_multi_textarea/frontend/build/static/js/main.e8672309.chunk.js
streamlit_multi_textarea/frontend/build/static/js/main.e8672309.chunk.js.map
streamlit_multi_textarea/frontend/build/static/js/runtime-main.1765f872.js
streamlit_multi_textarea/frontend/build/static/js/runtime-main.1765f872.js.map
streamlit_multi_row_inputs-0.0.4.dist-info/LICENSE
streamlit_multi_row_inputs-0.0.4.dist-info/METADATA
streamlit_multi_row_inputs-0.0.4.dist-info/WHEEL
streamlit_multi_row_inputs-0.0.4.dist-info/top_level.txt
streamlit_multi_row_inputs-0.0.4.dist-info/RECORD
