Metadata-Version: 2.1
Name: streamlit-multi-row-inputs
Version: 0.0.4
Summary: Streamlit componenet can contain multiple row inputs
Home-page: UNKNOWN
Author: Planete
Author-email: ytw0113@gmail.com
License: UNKNOWN
Platform: UNKNOWN
Requires-Python: >=3.6
License-File: LICENSE
Requires-Dist: streamlit (>=0.63)
